netbox_ddns/__init__.py
netbox_ddns/admin.py
netbox_ddns/background_tasks.py
netbox_ddns/filtersets.py
netbox_ddns/forms.py
netbox_ddns/models.py
netbox_ddns/navigation.py
netbox_ddns/search.py
netbox_ddns/signals.py
netbox_ddns/tables.py
netbox_ddns/template_content.py
netbox_ddns/urls.py
netbox_ddns/utils.py
netbox_ddns/validators.py
netbox_ddns/views.py
netbox_ddns/api/__init__.py
netbox_ddns/api/serializers.py
netbox_ddns/api/urls.py
netbox_ddns/api/views.py
netbox_ddns/migrations/0001_initial.py
netbox_ddns/migrations/0002_add_ttl.py
netbox_ddns/migrations/0003_dnsstatus.py
netbox_ddns/migrations/0004_ensure_trailing_dot.py
netbox_ddns/migrations/0005_extradnsname.py
netbox_ddns/migrations/0006_extradns_cname.py
netbox_ddns/migrations/0007_zone_meta.py
netbox_ddns/migrations/0008_server_server_port.py
netbox_ddns/migrations/0009_alter_dnsstatus_id_alter_extradnsname_id_and_more.py
netbox_ddns/migrations/0010_extradnsname_created_extradnsname_custom_field_data_and_more.py
netbox_ddns/migrations/0011_server_created_server_custom_field_data_and_more.py
netbox_ddns/migrations/0012_zone_created_zone_custom_field_data_and_more.py
netbox_ddns/migrations/0013_reversezone_created_reversezone_custom_field_data_and_more.py
netbox_ddns/migrations/__init__.py
netbox_ddns/templates/netbox_ddns/extradnsname.html
netbox_ddns/templates/netbox_ddns/reversezone.html
netbox_ddns/templates/netbox_ddns/server.html
netbox_ddns/templates/netbox_ddns/update_reverse_zone.html
netbox_ddns/templates/netbox_ddns/update_zone.html
netbox_ddns/templates/netbox_ddns/zone.html
netbox_ddns/templates/netbox_ddns/ipaddress/dns_extra.html
netbox_ddns/templates/netbox_ddns/ipaddress/dns_info.html
netbox_ddns/templates/netbox_ddns/ipaddress/dns_refresh_button.html
netbox_ddns-1.5.0.dist-info/LICENSE.txt
netbox_ddns-1.5.0.dist-info/METADATA
netbox_ddns-1.5.0.dist-info/WHEEL
netbox_ddns-1.5.0.dist-info/top_level.txt
netbox_ddns-1.5.0.dist-info/RECORD
