Metadata-Version: 2.2
Name: netbox-ddns
Version: 1.5.0
Summary: Dynamic DNS Connector for NetBox
Home-page: https://github.com/sjm-steffann/netbox-ddns
Author: Sander Steffann
Author-email: sander@steffann.nl
License: Apache 2.0
Classifier: Development Status :: 2 - Pre-Alpha
Classifier: Framework :: Django
Classifier: Framework :: Django :: 3.0
Classifier: License :: OSI Approved :: Apache Software License
Classifier: Programming Language :: Python :: 3
Classifier: Programming Language :: Python :: 3.6
Requires-Python: >=3.10
License-File: LICENSE.txt
Requires-Dist: setuptools
Requires-Dist: dnspython
